onto_match/__init__.py
onto_match/entrypoints.py
onto_match/models.py
onto_match/retrievers.py
onto_match/rules.py
onto_match/utils.py
onto_match-0.0.2.dist-info/LICENSE
onto_match-0.0.2.dist-info/METADATA
onto_match-0.0.2.dist-info/WHEEL
onto_match-0.0.2.dist-info/RECORD
