Metadata-Version: 2.1
Name: onto_match
Version: 0.0.2
Summary: Check if RDF data aligns with an ontology.
Home-page: https://github.com/atomobianco/onto-match
Author: Tommaso Bianco
Author-email: tommaso.bianco@gmail.com
Requires-Python: >=3.9,<4.0
Classifier: Programming Language :: Python :: 3
Classifier: Programming Language :: Python :: 3.9
Classifier: Programming Language :: Python :: 3.10
Classifier: Programming Language :: Python :: 3.11
Classifier: Programming Language :: Python :: 3.12
Requires-Dist: rdflib (>=7.0.0,<8.0.0)
Project-URL: Documentation, https://atomobianco.github.io/onto-match/
Project-URL: Repository, https://github.com/atomobianco/onto-match
